pyofwar/__init__.py
pyofwar/pow.py
pyofwar/quote_list.py
pyofwar-1.0.0.dist-info/LICENSE
pyofwar-1.0.0.dist-info/METADATA
pyofwar-1.0.0.dist-info/WHEEL
pyofwar-1.0.0.dist-info/top_level.txt
pyofwar-1.0.0.dist-info/RECORD
