Metadata-Version: 2.1
Name: pyofwar
Version: 1.0.0
Summary: Python module for Sun Tzu's most popular quotes
Author-email: iJakub <jakub.izdebski.social@gmail.com>
Project-URL: Homepage, https://github.com/iJakub/pyofwar
Project-URL: Bug Tracker, https://github.com/iJakub/pyofwar/issues
Classifier: Programming Language :: Python :: 3
Classifier: License :: OSI Approved :: GNU Affero General Public License v3
Classifier: Operating System :: OS Independent
Requires-Python: >=3.7
License-File: LICENSE
